cloudworker/__init__.py
cloudworker/worker.py
cloudkit_worker-1.0.dist-info/METADATA
cloudkit_worker-1.0.dist-info/WHEEL
cloudkit_worker-1.0.dist-info/top_level.txt
cloudkit_worker-1.0.dist-info/RECORD
