Metadata-Version: 2.1
Name: cloudkit-worker
Version: 1.0
Requires-Dist: websocket-client
